[
  {
    "Id": 1,
    "title": "TechCorp Enterprise Package",
    "leadId": "1",
    "stage": "proposal",
    "value": 25000,
    "probability": 75,
    "expectedCloseDate": "2024-02-15",
    "assignedTo": "John Smith",
    "createdAt": "2024-01-15T10:00:00Z",
    "updatedAt": "2024-01-18T14:30:00Z",
    "notes": "Proposal sent. Waiting for stakeholder review. Very promising."
  },
  {
    "Id": 2,
    "title": "InnovateDev API Integration",
    "leadId": "2",
    "stage": "qualified",
    "value": 45000,
    "probability": 60,
    "expectedCloseDate": "2024-02-28",
    "assignedTo": "Sarah Williams",
    "createdAt": "2024-01-16T09:30:00Z",
    "updatedAt": "2024-01-17T11:45:00Z",
    "notes": "Technical requirements gathering complete. Demo went well."
  },
  {
    "Id": 3,
    "title": "GlobalTech Enterprise Solution",
    "leadId": "4",
    "stage": "negotiation",
    "value": 75000,
    "probability": 80,
    "expectedCloseDate": "2024-03-30",
    "assignedTo": "Lisa Anderson",
    "createdAt": "2024-01-10T08:15:00Z",
    "updatedAt": "2024-01-19T13:20:00Z",
    "notes": "In final negotiations. Pricing discussions ongoing. Legal review started."
  },
  {
    "Id": 4,
    "title": "StartupLab Team Package",
    "leadId": "3",
    "stage": "new",
    "value": 15000,
    "probability": 25,
    "expectedCloseDate": "2024-02-20",
    "assignedTo": "Mike Davis",
    "createdAt": "2024-01-18T16:20:00Z",
    "updatedAt": "2024-01-18T16:20:00Z",
    "notes": "Initial interest shown. Need to schedule discovery call."
  },
  {
    "Id": 5,
    "title": "HealthTech Compliance Suite",
    "leadId": "7",
    "stage": "qualified",
    "value": 32000,
    "probability": 50,
    "expectedCloseDate": "2024-03-15",
    "assignedTo": "Mike Davis",
    "createdAt": "2024-01-19T11:20:00Z",
    "updatedAt": "2024-01-19T11:20:00Z",
    "notes": "Healthcare compliance requirements identified. Solution fits well."
  },
  {
    "Id": 6,
    "title": "RetailPlus Multi-Location",
    "leadId": "8",
    "stage": "proposal",
    "value": 18000,
    "probability": 65,
    "expectedCloseDate": "2024-02-25",
    "assignedTo": "Lisa Anderson",
    "createdAt": "2024-01-14T15:10:00Z",
    "updatedAt": "2024-01-16T10:20:00Z",
    "notes": "Proposal for multi-location setup. Good engagement from decision makers."
  },
  {
    "Id": 7,
    "title": "MarketLeader Expansion",
    "leadId": "9",
    "stage": "closed_won",
    "value": 50000,
    "probability": 100,
    "expectedCloseDate": "2024-01-20",
    "assignedTo": "John Smith",
    "createdAt": "2024-01-05T09:00:00Z",
    "updatedAt": "2024-01-20T16:00:00Z",
    "notes": "Deal closed successfully! Implementation to start next month."
  },
  {
    "Id": 8,
    "title": "SmallBiz Basic Package",
    "leadId": "10",
    "stage": "closed_lost",
    "value": 5000,
    "probability": 0,
    "expectedCloseDate": "2024-01-25",
    "assignedTo": "Sarah Williams",
    "createdAt": "2024-01-08T11:30:00Z",
    "updatedAt": "2024-01-25T14:15:00Z",
    "notes": "Lost to competitor. Price was the main factor. Lessons learned documented."
  }
]